gistrun/__about__.py
gistrun/__init__.py
gistrun/__main__.py
gistrun/cli/__init__.py
gistrun-1.0.14.dist-info/METADATA
gistrun-1.0.14.dist-info/WHEEL
gistrun-1.0.14.dist-info/entry_points.txt
gistrun-1.0.14.dist-info/licenses/LICENSE
gistrun-1.0.14.dist-info/RECORD
