Metadata-Version: 2.3
Name: gistrun
Version: 1.0.14
Project-URL: Documentation, https://github.com/drengskapur/gistrun#readme
Project-URL: Issues, https://github.com/drengskapur/gistrun/issues
Project-URL: Source, https://github.com/drengskapur/gistrun
Author-email: drengskapur <service@drengskapur.com>
License-Expression: GPL-3.0-or-later
License-File: LICENSE
Classifier: Development Status :: 4 - Beta
Classifier: Programming Language :: Python
Classifier: Programming Language :: Python :: 3.8
Classifier: Programming Language :: Python :: 3.9
Classifier: Programming Language :: Python :: 3.10
Classifier: Programming Language :: Python :: 3.11
Classifier: Programming Language :: Python :: 3.12
Classifier: Programming Language :: Python :: Implementation :: CPython
Classifier: Programming Language :: Python :: Implementation :: PyPy
Requires-Python: >=3.8
Requires-Dist: click==8.1.7
Requires-Dist: requests==2.31.0
